datasette_packages/__init__.py
datasette_packages-0.2.1.dist-info/LICENSE
datasette_packages-0.2.1.dist-info/METADATA
datasette_packages-0.2.1.dist-info/WHEEL
datasette_packages-0.2.1.dist-info/entry_points.txt
datasette_packages-0.2.1.dist-info/top_level.txt
datasette_packages-0.2.1.dist-info/RECORD
