Metadata-Version: 2.1
Name: datasette-packages
Version: 0.2.1
Summary: Show a list of currently installed Python packages
Home-page: https://github.com/simonw/datasette-packages
Author: Simon Willison
License: Apache License, Version 2.0
Project-URL: Issues, https://github.com/simonw/datasette-packages/issues
Project-URL: CI, https://github.com/simonw/datasette-packages/actions
Project-URL: Changelog, https://github.com/simonw/datasette-packages/releases
Classifier: Framework :: Datasette
Classifier: License :: OSI Approved :: Apache Software License
Requires-Python: >=3.8
License-File: LICENSE
Requires-Dist: datasette
Provides-Extra: test
Requires-Dist: pytest ; extra == 'test'
Requires-Dist: pytest-asyncio ; extra == 'test'
Requires-Dist: datasette-graphql >=2.1 ; extra == 'test'
